{"ef": [{"p": 330, "h": 150, "v": 2.0202020202020203e-05}, {"p": 300, "h": 160, "v": 2.0833333333333336e-05}, {"p": 0, "h": 150, "v": 0.0}, {"p": 330, "h": 0, "v": 0.0}, {"p": 270, "h": 140, "v": 2.6455026455026456e-05}], "decoupling": [{"a": {"pace_sec_km": 330, "avg_hr": 150}, "b": {"pace_sec_km": 345, "avg_hr": 158}, "v": 9.19097413318658}, {"a": {"pace_sec_km": 330, "avg_hr": 150}, "b": {"pace_sec_km": 320, "avg_hr": 148}, "v": -4.518581081081083}, {"a": {"pace_sec_km": 330, "avg_hr": 0}, "b": {"pace_sec_km": 345, "avg_hr": 158}, "v": 0.0}], "vo2": [{"in": [{"generic": {"vo2MaxPreciseValue": 52.3}}], "v": 52.3}, {"in": [{"vo2MaxPreciseValue": 48.1}], "v": 48.1}, {"in": {"generic": {"vo2MaxPreciseValue": 55.0}}, "v": 55.0}, {"in": {"vo2MaxPreciseValue": 41.2}, "v": 41.2}, {"in": [], "v": null}, {"in": [{"foo": 1}], "v": null}, {"in": {"generic": {}}, "v": null}], "halves": [{"in": {"lapDTOs": [{"distance": 1000, "duration": 330, "averageHR": 150}, {"distance": 1000, "duration": 335, "averageHR": 152}, {"distance": 1000, "duration": 340, "averageHR": 156}, {"distance": 1000, "duration": 345, "averageHR": 158}]}, "v": [{"pace_sec_km": 332.5, "avg_hr": 151.00751879699249}, {"pace_sec_km": 342.5, "avg_hr": 157.007299270073}]}, {"in": {"splitSummaries": [{"distance": 1000, "duration": 320, "averageHeartRate": 148}, {"distance": 1000, "duration": 330, "averageHeartRate": 151}]}, "v": [{"pace_sec_km": 320.0, "avg_hr": 148.0}, {"pace_sec_km": 330.0, "avg_hr": 151.0}]}], "aggregate": [{"in": [{"distance": 1000, "duration": 330, "averageHR": 150}, {"distance": 1000, "duration": 340, "averageHR": 155}], "v": {"pace_sec_km": 335.0, "avg_hr": 152.53731343283582}}, {"in": [{"distance": 0, "duration": 0, "averageHR": 0}], "v": null}]}
