{"z_score": [{"in": {"v": 50.0, "b": [45, 46, 47, 48, 49, 50, 51, 52]}, "v": 0.6546536707079772}, {"in": {"v": 30.0, "b": [45, 46, 47, 48, 49, 50, 51, 52]}, "v": -8.074061938731719}, {"in": {"v": 50.0, "b": [50, 50, 50, 50, 50, 50, 50]}, "v": 0.0}, {"in": {"v": 50.0, "b": [1, 2, 3]}, "v": 0.0}, {"in": {"v": 6.5, "b": [7.0, 7.2, 6.8, 7.1, 6.9, 7.3, 7.0, 6.7, 7.4]}, "v": -2.5136469626086266}], "readiness": [{"in": {"hrv_z": 0.5, "sleep_z": 0.2, "rhr_z": 0.1, "bb_z": 0.3, "sleep_hours": 7.5, "body_battery_morning": 60}, "v": {"hrv_z_score": 0.5, "sleep_z_score": 0.2, "rhr_z_score": 0.1, "body_battery_z_score": 0.3, "composite_score": 0.275, "traffic_light": "green", "flags": []}}, {"in": {"hrv_z": 0.5, "sleep_z": -0.2, "rhr_z": 0.1, "bb_z": 0.3, "sleep_hours": 4.5, "body_battery_morning": 60}, "v": {"hrv_z_score": 0.5, "sleep_z_score": -0.2, "rhr_z_score": 0.1, "body_battery_z_score": 0.3, "composite_score": 0.175, "traffic_light": "red", "flags": ["sleep_under_5h"]}}, {"in": {"hrv_z": 0.5, "sleep_z": 0.2, "rhr_z": 0.1, "bb_z": -0.3, "sleep_hours": 7.5, "body_battery_morning": 20}, "v": {"hrv_z_score": 0.5, "sleep_z_score": 0.2, "rhr_z_score": 0.1, "body_battery_z_score": -0.3, "composite_score": 0.125, "traffic_light": "red", "flags": ["body_battery_critical"]}}, {"in": {"hrv_z": -1.5, "sleep_z": -1.2, "rhr_z": 0.1, "bb_z": 0.3, "sleep_hours": 7.5, "body_battery_morning": 60}, "v": {"hrv_z_score": -1.5, "sleep_z_score": -1.2, "rhr_z_score": 0.1, "body_battery_z_score": 0.3, "composite_score": -0.575, "traffic_light": "yellow", "flags": ["hrv_below_swc", "2_of_4_flagged"]}}, {"in": {"hrv_z": -1.5, "sleep_z": -1.2, "rhr_z": -1.1, "bb_z": 0.3, "sleep_hours": 7.5, "body_battery_morning": 60}, "v": {"hrv_z_score": -1.5, "sleep_z_score": -1.2, "rhr_z_score": -1.1, "body_battery_z_score": 0.3, "composite_score": -0.875, "traffic_light": "red", "flags": ["hrv_below_swc", "3_of_4_flagged"]}}, {"in": {"hrv_z": -0.7, "sleep_z": 0.2, "rhr_z": 0.1, "bb_z": 0.3, "sleep_hours": 7.5, "body_battery_morning": 60}, "v": {"hrv_z_score": -0.7, "sleep_z_score": 0.2, "rhr_z_score": 0.1, "body_battery_z_score": 0.3, "composite_score": -0.025, "traffic_light": "green", "flags": ["hrv_below_swc"]}}, {"in": {"hrv_z": null, "sleep_z": -1.2, "rhr_z": null, "bb_z": 0.3, "sleep_hours": 7.5, "body_battery_morning": 60}, "v": {"hrv_z_score": null, "sleep_z_score": -1.2, "rhr_z_score": null, "body_battery_z_score": 0.3, "composite_score": -0.45, "traffic_light": "green", "flags": []}}, {"in": {"hrv_z": 0.1, "sleep_z": 0.1, "rhr_z": 0.1, "bb_z": 0.1, "sleep_hours": 7.5, "body_battery_morning": null}, "v": {"hrv_z_score": 0.1, "sleep_z_score": 0.1, "rhr_z_score": 0.1, "body_battery_z_score": 0.1, "composite_score": 0.1, "traffic_light": "green", "flags": []}}]}
